README.rst
setup.py
es_cli/__init__.py
es_cli/cli.py
es_cli/utils.py
es_cli.egg-info/PKG-INFO
es_cli.egg-info/SOURCES.txt
es_cli.egg-info/dependency_links.txt
es_cli.egg-info/entry_points.txt
es_cli.egg-info/not-zip-safe
es_cli.egg-info/requires.txt
es_cli.egg-info/top_level.txt