Metadata-Version: 1.1
Name: es-cli
Version: 0.0.2
Summary: Small Elasticsearch management cli
Home-page: https://github.com/inspirehep/es-cli
Author: CERN
Author-email: admin@inspirehep.net
License: GPLv2
Platform: UNKNOWN
Classifier: Intended Audience :: Developers
Classifier: License :: OSI Approved :: GNU General Public License v2 (GPLv2)
Classifier: Operating System :: OS Independent
Classifier: Programming Language :: Python
Classifier: Topic :: Software Development :: Libraries :: Python Modules
Classifier: Programming Language :: Python :: 2
Classifier: Programming Language :: Python :: 2.7
Classifier: Development Status :: 4 - Beta
